c4m/pdk/ihpsg13g2/__init__.py
c4m/pdk/ihpsg13g2/_io_compliance.py
c4m/pdk/ihpsg13g2/io.py
c4m/pdk/ihpsg13g2/klayout.py
c4m/pdk/ihpsg13g2/models/__init__.py
c4m/pdk/ihpsg13g2/models/all.spice
c4m/pdk/ihpsg13g2/models/cornerMOShv.lib
c4m/pdk/ihpsg13g2/models/cornerMOSlv.lib
c4m/pdk/ihpsg13g2/models/cornerRES.lib
c4m/pdk/ihpsg13g2/models/diodes.lib
c4m/pdk/ihpsg13g2/models/resistors_mod.lib
c4m/pdk/ihpsg13g2/models/resistors_parm.lib
c4m/pdk/ihpsg13g2/models/resistors_stat.lib
c4m/pdk/ihpsg13g2/models/sg13g2_moshv_mod.lib
c4m/pdk/ihpsg13g2/models/sg13g2_moshv_parm.lib
c4m/pdk/ihpsg13g2/models/sg13g2_moshv_stat.lib
c4m/pdk/ihpsg13g2/models/sg13g2_moslv_mod.lib
c4m/pdk/ihpsg13g2/models/sg13g2_moslv_parm.lib
c4m/pdk/ihpsg13g2/models/sg13g2_moslv_stat.lib
c4m/pdk/ihpsg13g2/pdkmaster.py
c4m/pdk/ihpsg13g2/pyspice.py
c4m/pdk/ihpsg13g2/spice.py
c4m/pdk/ihpsg13g2/stdcell.py
c4m_pdk_ihpsg13g2-0.1.3.dist-info/METADATA
c4m_pdk_ihpsg13g2-0.1.3.dist-info/WHEEL
c4m_pdk_ihpsg13g2-0.1.3.dist-info/entry_points.txt
c4m_pdk_ihpsg13g2-0.1.3.dist-info/licenses/LICENSE.md
c4m_pdk_ihpsg13g2-0.1.3.dist-info/RECORD
