Metadata-Version: 2.1
Name: c4m-pdk-ihpsg13g2
Version: 0.1.3
Summary: PDKMaster based PDK for open source IHP SG13G2 process
Author: Chips4Makers contributors
License: GPL-2.0-or-later OR AGPL-3.0-or-later OR CERN-OHL-S-2.0+
Requires-Python: ~=3.8
Requires-Dist: PDKMaster~=0.12.0
Requires-Dist: pdkmaster-io-spice~=0.1.0
Requires-Dist: pdkmaster-io-klayout~=0.1.7
Requires-Dist: c4m-flexcell~=0.4.6
Requires-Dist: c4m-flexio~=0.4.9
